dstore/DStore.py
dstore/__init__.py
dstore/dstProcessor.py
dstore/relationalMapper.py
dstore_orm-0.0.1.dist-info/LICENSE
dstore_orm-0.0.1.dist-info/METADATA
dstore_orm-0.0.1.dist-info/WHEEL
dstore_orm-0.0.1.dist-info/top_level.txt
dstore_orm-0.0.1.dist-info/RECORD
