Metadata-Version: 2.1
Name: dstore-orm
Version: 0.0.1
Summary: A simple ORM for Sqlite3
Home-page: https://github.com/GracePeterMutiibwa/dstore-orm
Author: The Big Engineer (Mutiibwa Grace Peter), Blessing Tukasiima
Author-email: <dstore.orm.helpdesk@gmail.com>
License: MIT
Keywords: python,sqlite3,orm,sqlite3 orm,save objects,save objects in Python
Classifier: License :: OSI Approved :: MIT License
Classifier: Development Status :: 4 - Beta
Classifier: Intended Audience :: Developers
Classifier: Programming Language :: Python :: 3
Classifier: Operating System :: Unix
Classifier: Operating System :: MacOS :: MacOS X
Classifier: Operating System :: Microsoft :: Windows
Requires-Python: >=3.6.0
License-File: LICENSE
